odoo8_addon_invoice_fiscal_position_update-8.0.1.0.0.99.dev17-py2.7-nspkg.pth
odoo8_addon_invoice_fiscal_position_update-8.0.1.0.0.99.dev17.dist-info/METADATA
odoo8_addon_invoice_fiscal_position_update-8.0.1.0.0.99.dev17.dist-info/RECORD
odoo8_addon_invoice_fiscal_position_update-8.0.1.0.0.99.dev17.dist-info/WHEEL
odoo8_addon_invoice_fiscal_position_update-8.0.1.0.0.99.dev17.dist-info/namespace_packages.txt
odoo8_addon_invoice_fiscal_position_update-8.0.1.0.0.99.dev17.dist-info/top_level.txt
odoo_addons/invoice_fiscal_position_update/__init__.py
odoo_addons/invoice_fiscal_position_update/__openerp__.py
odoo_addons/invoice_fiscal_position_update/account_invoice.py
odoo_addons/invoice_fiscal_position_update/i18n/ar.po
odoo_addons/invoice_fiscal_position_update/i18n/bg.po
odoo_addons/invoice_fiscal_position_update/i18n/bs.po
odoo_addons/invoice_fiscal_position_update/i18n/ca.po
odoo_addons/invoice_fiscal_position_update/i18n/cs.po
odoo_addons/invoice_fiscal_position_update/i18n/de.po
odoo_addons/invoice_fiscal_position_update/i18n/el_GR.po
odoo_addons/invoice_fiscal_position_update/i18n/en_GB.po
odoo_addons/invoice_fiscal_position_update/i18n/es.po
odoo_addons/invoice_fiscal_position_update/i18n/es_CR.po
odoo_addons/invoice_fiscal_position_update/i18n/es_EC.po
odoo_addons/invoice_fiscal_position_update/i18n/es_MX.po
odoo_addons/invoice_fiscal_position_update/i18n/es_PE.po
odoo_addons/invoice_fiscal_position_update/i18n/et.po
odoo_addons/invoice_fiscal_position_update/i18n/eu.po
odoo_addons/invoice_fiscal_position_update/i18n/fi.po
odoo_addons/invoice_fiscal_position_update/i18n/fr.po
odoo_addons/invoice_fiscal_position_update/i18n/fr_CA.po
odoo_addons/invoice_fiscal_position_update/i18n/fr_CH.po
odoo_addons/invoice_fiscal_position_update/i18n/gl.po
odoo_addons/invoice_fiscal_position_update/i18n/hr.po
odoo_addons/invoice_fiscal_position_update/i18n/hr_HR.po
odoo_addons/invoice_fiscal_position_update/i18n/hu.po
odoo_addons/invoice_fiscal_position_update/i18n/id.po
odoo_addons/invoice_fiscal_position_update/i18n/it.po
odoo_addons/invoice_fiscal_position_update/i18n/ja.po
odoo_addons/invoice_fiscal_position_update/i18n/lt.po
odoo_addons/invoice_fiscal_position_update/i18n/mk.po
odoo_addons/invoice_fiscal_position_update/i18n/mn.po
odoo_addons/invoice_fiscal_position_update/i18n/nb.po
odoo_addons/invoice_fiscal_position_update/i18n/nb_NO.po
