Metadata-Version: 2.1
Name: odoo8-addon-invoice-fiscal-position-update
Version: 8.0.1.0.0.99.dev17
Summary: Changing the fiscal position of an invoice will auto-update invoice lines
Home-page: UNKNOWN
Author: Julius Network Solutions,Akretion,Odoo Community Association (OCA)
Author-email: support@odoo-community.org
License: AGPL-3
Platform: UNKNOWN
Classifier: Programming Language :: Python
Classifier: Framework :: Odoo
Classifier: License :: OSI Approved :: GNU Affero General Public License v3
Requires-Python: ~=2.7
Requires-Dist: odoo (<9.0a,>=8.0a)
